Calculator/Accumulator.vhd
library ieee;
use ieee.std_logic_1164.all;
use ieee.numeric_std.all;

entity Accumulator is
    port (
        clk         : in  std_logic;
        rst         : in  std_logic; -- Low active reset
        ac_init        : in  std_logic; -- High active init
        ac_enable      : in  std_logic; -- High active enable
        data_in     : in  signed(15 downto 0);
        result_out  : out signed(15 downto 0)
    );
end entity Accumulator;

architecture Behavioral of Accumulator is
begin
    process(clk, rst)
    begin
        if rst = '0' then
            result_out <= (others => '0');
        elsif rising_edge(clk) then
            -- Since not all the combinations are exploited, the VHDL simulator creates a memory element which stores the previous value
            if ac_init = '1' then
                result_out <= (others => '0');
            elsif ac_enable = '1' then
                result_out <= data_in;
            end if;
        end if;
    end process;
end architecture Behavioral;

Calculator/accumulator_testbench.vhd
----------------------------------------------------------------------------------
-- Company:
-- Engineer:
--
-- Create Date: 04/25/2020 04:57:11 PM
-- Design Name:
-- Module Name: accumulator_testbench - Behavioral
-- Project Name:
-- Target Devices:
-- Tool Versions:
-- Description:
--
-- Dependencies:
--
-- Revision:
-- Revision 0.01 - File Created
-- Additional Comments:
--
----------------------------------------------------------------------------------


library IEEE;
use IEEE.STD_LOGIC_1164.ALL;

-- Uncomment the following library declaration if using
-- arithmetic functions with Signed or Unsigned values
use IEEE.NUMERIC_STD.ALL;

-- Uncomment the following library declaration if instantiating
-- any Xilinx leaf cells in this code.
--library UNISIM;
--use UNISIM.VComponents.all;

entity accumulator_testbench is
--  Port ( );
end accumulator_testbench;

architecture Behavioral of accumulator_testbench is

component Accumulator
  Port (
    clk         : in  std_logic;
    rst         : in  std_logic;
    ac_init        : in  std_logic;
    ac_enable      : in  std_logic;
    data_in     : in  signed(15 downto 0);
    result_out  : out signed(15 downto 0)
  );
end component;

signal clock : std_logic := '0';
signal reset : std_logic := '0';
signal acc_init : std_logic := '0';
signal acc_enable : std_logic := '0';
signal acc_in : signed(15 downto 0) := (others => '0');
signal acc_out : signed(15 downto 0) := (others => '0');

begin

 uut : Accumulator
 port map(
    clk      => clock,
    rst      => reset,
    ac_init   => acc_init,
    ac_enable => acc_enable,
    data_in    => acc_in,
    result_out    => acc_out
 );

 clock <= not(clock) after 5 ns;

 uut_test_proc : process
 begin

    reset <= '0';
    wait for 20 ns;
    reset <= '1';

    wait for 10 ns;

    acc_in <= "0000000000000011"; --3
    wait for 10 ns;

    acc_enable <= '1';
    wait for 10 ns;
    acc_enable <= '0';

    wait for 50 ns;

    acc_init <= '1';
    wait for 10 ns;
    acc_init <= '0';

 wait;
 end process;

end Behavioral;

Calculator/acccumulator_tb.vcd
$date
  Tue Dec  2 15:48:13 2025
$end
$version
  GHDL v0
$end
$timescale
  1 fs
$end
$scope module standard $end
$upscope $end
$scope module std_logic_1164 $end
$upscope $end
$scope module numeric_std $end
$upscope $end
$scope module accumulator_testbench $end
$var reg 1 ! clock $end
$var reg 1 " reset $end
$var reg 1 # acc_init $end
$var reg 1 $ acc_enable $end
$var reg 16 % acc_in[15:0] $end
$var reg 16 & acc_out[15:0] $end
$scope module uut $end
$var reg 1 ' clk $end
$var reg 1 ( rst $end
$var reg 1 ) ac_init $end
$var reg 1 * ac_enable $end
$var reg 16 + data_in[15:0] $end
$var reg 16 , result_out[15:0] $end
$upscope $end
$upscope $end
$enddefinitions $end
#0
0!
0"
0#
0$
b0000000000000000 %
b0000000000000000 &
0'
0(
0)
0*
b0000000000000000 +
b0000000000000000 ,
#5000000
1!
1'
#10000000
0!
0'
#15000000
1!
1'
#20000000
0!
1"
0'
1(
#25000000
1!
1'
#30000000
0!
b0000000000000011 %
0'
b0000000000000011 +
#35000000
1!
1'
#40000000
0!
1$
0'
1*
#45000000
1!
b0000000000000011 &
1'
b0000000000000011 ,
#50000000
0!
0$
0'
0*
#55000000
1!
1'
#60000000
0!
0'
#65000000
1!
1'
#70000000
0!
0'
#75000000
1!
1'
#80000000
0!
0'
#85000000
1!
1'
#90000000
0!
0'
#95000000
1!
1'
#100000000
0!
1#
0'
1)
#105000000
1!
b0000000000000000 &
1'
b0000000000000000 ,
#110000000
0!
0#
0'
0)
