Calculator/ALU.vhd
library IEEE;
use IEEE.STD_LOGIC_1164.ALL;
use IEEE.NUMERIC_STD.ALL;

-- ALU entity definition: inputs must take the sign into account
entity ALU is
    Port (
        a        : in  signed( 15 downto 0 );
        b        : in  signed( 15 downto 0 );  
        add      : in  std_logic;
        subtract : in  std_logic;
        multiply : in  std_logic;
        divide   : in  std_logic;
        r        : out signed( 15 downto 0 )
    );
end ALU;

-- ALU architecture definition
architecture Behavioral of ALU is
    signal temp_res : signed(31 downto 0);
begin

    process (a, b, add, subtract, multiply, divide, temp_res)
    begin
        r <= (others => '0');  -- default assignment

        if add = '1' then
        r <= a + b;

        elsif subtract = '1' then
        r <= a - b;

        elsif multiply = '1' then
        temp_res <= a * b;
        r <= temp_res(15 downto 0);  -- lower 16 bits

        elsif divide = '1' then
        r <= a / b;

        end if;
    end process;

end Behavioral;

Calculator/alu_testbench.vhd
library IEEE;
use IEEE.STD_LOGIC_1164.ALL;
use IEEE.NUMERIC_STD.ALL;

entity alu_testbench is
--  Port ( );
end alu_testbench;

architecture Behavioral of alu_testbench is

component alu
  Port(
    a, b : in signed( 15 downto 0 );
    add, subtract, multiply, divide : in std_logic;
    r : out signed( 15 downto 0 )
  );
end component;

signal a : signed(15 downto 0) := (others => '0');
signal b : signed(15 downto 0) := (others => '0');
signal add, subtract, multiply, divide : std_logic := '0';
signal r : signed(15 downto 0) := (others => '0');

begin

   dut: alu
   port map(
      a        => a,
      b        => b,
      add      => add,
      subtract => subtract,
      multiply => multiply,
      divide   => divide,
      r        => r
   );

    alu_test_proc : process
    begin

     wait for 100 ns;

     a <= "0000000000000101"; -- 5
     b <= "0000000000000010"; -- 2

     wait for 10 ns;

     add <= '1';
     wait for 10 ns;
     add <= '0';
     wait for 10 ns;

     subtract <= '1';
     wait for 10 ns;
     subtract <= '0';
     wait for 10 ns;

     multiply <= '1';
     wait for 10 ns;
     multiply <= '0';
     wait for 10 ns;

     divide <= '1';
     wait for 10 ns;
     divide <= '0';
     wait for 10 ns;

    wait;
    end process;

end Behavioral;

Calculator/Alu_waves.vcd
$date
  Sun Jan 11 12:02:51 2026
$end
$version
  GHDL v0
$end
$timescale
  1 fs
$end
$scope module standard $end
$upscope $end
$scope module std_logic_1164 $end
$upscope $end
$scope module numeric_std $end
$upscope $end
$scope module alu_testbench $end
$var reg 16 ! a[15:0] $end
$var reg 16 " b[15:0] $end
$var reg 1 # add $end
$var reg 1 $ subtract $end
$var reg 1 % multiply $end
$var reg 1 & divide $end
$var reg 16 ' r[15:0] $end
$scope module dut $end
$var reg 16 ( a[15:0] $end
$var reg 16 ) b[15:0] $end
$var reg 1 * add $end
$var reg 1 + subtract $end
$var reg 1 , multiply $end
$var reg 1 - divide $end
$var reg 16 . r[15:0] $end
$var reg 32 / temp_res[31:0] $end
$upscope $end
$upscope $end
$enddefinitions $end
#0
b0000000000000000 !
b0000000000000000 "
0#
0$
0%
0&
b0000000000000000 '
b0000000000000000 (
b0000000000000000 )
0*
0+
0,
0-
b0000000000000000 .
bUUUUUUUUUUUUUUUUUUUUUUUUUUUUUUUU /
#100000000
b0000000000000101 !
b0000000000000010 "
b0000000000000101 (
b0000000000000010 )
#110000000
1#
b0000000000000111 '
1*
b0000000000000111 .
#120000000
0#
b0000000000000000 '
0*
b0000000000000000 .
#130000000
1$
b0000000000000011 '
1+
b0000000000000011 .
#140000000
0$
b0000000000000000 '
0+
b0000000000000000 .
#150000000
1%
b0000000000001010 '
1,
b0000000000001010 .
b00000000000000000000000000001010 /
#160000000
0%
b0000000000000000 '
0,
b0000000000000000 .
#170000000
1&
b0000000000000010 '
1-
b0000000000000010 .
#180000000
0&
b0000000000000000 '
0-
b0000000000000000 .
