Calculator/Debouncer.vhd
library ieee;
use ieee.std_logic_1164.all;
use ieee.numeric_std.all;

entity Debouncer is
    generic(
        counter_size : integer := 24
    );
    port (
        clk         : in  std_logic;
        rst         : in  std_logic;
        bouncy    : in  std_logic;
        pulse   : out std_logic
    );
end entity Debouncer;

architecture Behavioral of Debouncer is
    signal counter      : std_logic_vector(counter_size-1 downto 0) := (others => '1');
    signal prev_state   : std_logic := '0';
    signal outputting   : std_logic := '0';
begin
    process(clk, rst)
    begin
        if rst = '0' then
            counter    <= (others => '1');
            prev_state <= '0';
            pulse  <= '0';
            outputting <= '0';
        elsif rising_edge(clk) then
            if outputting = '1' then
                -- Output has been updated, wait for next change
                outputting <= '0';
                counter <= (others => '1');
                pulse <= '0';
            elsif bouncy /= prev_state then
                -- Button state changed, reset counter
                counter <= (others => '1');
                prev_state <= bouncy;
            else
                if unsigned(counter) > 0 then
                    counter <= std_logic_vector(unsigned(counter) - 1);
                else
                    -- Counter has expired, update clean output
                    pulse <= prev_state;
                    outputting <= '1';
                end if;
            end if;
        end if;
    end process;
end architecture Behavioral;

Calculator/debouncer_testbench.vhd
library IEEE;
use IEEE.STD_LOGIC_1164.ALL;

entity debouncer_testbench is
--  Port ( );
end debouncer_testbench;

architecture Behavioral of debouncer_testbench is

component Debouncer
  generic (
    counter_size : integer := 12
  );
  port (
    clk : in std_logic;
    rst : in std_logic;
    bouncy : in std_logic;
    pulse : out std_logic
  );
end component;

signal clk : std_logic := '0';
signal rst : std_logic := '0';
signal bouncy : std_logic := '0';
signal pulse : std_logic := '0';

begin

   dut : Debouncer
   port map(
      clk  => clk,
      rst  => rst,
      bouncy => bouncy,
      pulse   => pulse
   );

   clk <= not(clk) after 5 ns;

   dut_test_proc : process
   begin

      rst <= '0';
      wait for 10 ns;
      rst <= '1';
      wait for 10 ns;

      bouncy <= '0';
      wait for 10 ns;

      bouncy <= '1';
      wait for 10 ns;

      bouncy <= '0';
      wait for 10 ns;

      bouncy <= '1';
      wait for 15 us;

      bouncy <= '0';
      wait for 10 ns;

      bouncy <= '1';
      wait for 45 us;

      bouncy <= '0';
      wait for 100 ns;

   wait;
   end process;

end Behavioral;

Calculator/Debouncer_waves.vcd
$date
  Sun Jan 11 12:20:13 2026
$end
$version
  GHDL v0
$end
$timescale
  1 fs
$end
$scope module standard $end
$upscope $end
$scope module std_logic_1164 $end
$upscope $end
$scope module numeric_std $end
$upscope $end
$scope module debouncer_testbench $end
$var reg 1 ! clk $end
$var reg 1 " rst $end
$var reg 1 # bouncy $end
$var reg 1 $ pulse $end
$scope module dut $end
$var reg 1 % clk $end
$var reg 1 & rst $end
$var reg 1 ' bouncy $end
$var reg 1 ( pulse $end
$var reg 12 ) counter[11:0] $end
$var reg 1 * prev_state $end
$var reg 1 + outputting $end
$upscope $end
$upscope $end
$enddefinitions $end
#0
0!
0"
0#
0$
0%
0&
0'
0(
b111111111111 )
0*
0+
#5000000
1!
1%
#10000000
0!
1"
0%
1&
#15000000
1!
1%
b111111111110 )
#20000000
0!
0%
#25000000
1!
1%
b111111111101 )
#30000000
0!
1#
0%
1'
#35000000
1!
1%
b111111111111 )
1*
#40000000
0!
0#
0%
0'
#45000000
1!
1%
0*
#50000000
0!
1#
0%
1'
#55000000
1!
1%
1*
#60000000
0!
0%
#65000000
1!
1%
b111111111110 )
#70000000
0!
0%
#75000000
1!
1%
b111111111101 )
#80000000
0!
0%
#85000000
1!
1%
b111111111100 )
#90000000
0!
0%
#95000000
1!
1%
b111111111011 )
#100000000
0!
0%
#105000000
1!
1%
b111111111010 )
#110000000
0!
0%
#115000000
1!
1%
b111111111001 )
#120000000
0!
0%
#125000000
1!
1%
b111111111000 )
#130000000
0!
0%
#135000000
1!
1%
b111111110111 )
#140000000
0!
0%
#145000000
1!
1%
b111111110110 )
#150000000
0!
0%
#155000000
1!
1%
b111111110101 )
#160000000
0!
0%
#165000000
1!
1%
b111111110100 )
#170000000
0!
0%
#175000000
1!
1%
b111111110011 )
#180000000
0!
0%
#185000000
1!
1%
b111111110010 )
#190000000
0!
0%
#195000000
1!
1%
b111111110001 )
#200000000
0!
0%
#205000000
1!
1%
b111111110000 )
#210000000
0!
0%
#215000000
1!
1%
b111111101111 )
#220000000
0!
0%
#225000000
1!
1%
b111111101110 )
#230000000
0!
0%
#235000000
1!
1%
b111111101101 )
#240000000
0!
0%
#245000000
1!
1%
b111111101100 )
#250000000
0!
0%
#255000000
1!
1%
b111111101011 )
#260000000
0!
0%
#265000000
1!
1%
b111111101010 )
#270000000
0!
0%
#275000000
1!
1%
b111111101001 )
#280000000
0!
0%
#285000000
1!
1%
b111111101000 )
#290000000
0!
0%
#295000000
1!
1%
b111111100111 )
#300000000
0!
0%
#305000000
1!
1%
b111111100110 )
#310000000
0!
0%
#315000000
1!
1%
b111111100101 )
#320000000
0!
0%
#325000000
1!
1%
b111111100100 )
#330000000
0!
0%
#335000000
1!
1%
b111111100011 )
#340000000
0!
0%
#345000000
1!
1%
b111111100010 )
#350000000
0!
0%
#355000000
1!
1%
b111111100001 )
#360000000
0!
0%
#365000000
1!
1%
b111111100000 )
#370000000
0!
0%
#375000000
1!
1%
b111111011111 )
#380000000
0!
0%
#385000000
1!
1%
b111111011110 )
#390000000
0!
0%
#395000000
1!
1%
b111111011101 )
#400000000
0!
0%
#405000000
1!
1%
b111111011100 )
#410000000
0!
0%
#415000000
1!
1%
b111111011011 )
#420000000
0!
0%
#425000000
1!
1%
b111111011010 )
#430000000
0!
0%
#435000000
1!
1%
b111111011001 )
#440000000
0!
0%
#445000000
1!
1%
b111111011000 )
#450000000
0!
0%
#455000000
1!
1%
b111111010111 )
#460000000
0!
0%
#465000000
1!
1%
b111111010110 )
#470000000
0!
0%
#475000000
1!
1%
b111111010101 )
#480000000
0!
0%
#485000000
1!
1%
b111111010100 )
#490000000
0!
0%
#495000000
1!
1%
b111111010011 )
#500000000
0!
0%
#505000000
1!
1%
b111111010010 )
#510000000
0!
0%
#515000000
1!
1%
b111111010001 )
#520000000
0!
0%
#525000000
1!
1%
b111111010000 )
#530000000
0!
0%
#535000000
1!
1%
b111111001111 )
#540000000
0!
0%
#545000000
1!
1%
b111111001110 )
#550000000
0!
0%
#555000000
1!
1%
b111111001101 )
#560000000
0!
0%
#565000000
1!
1%
b111111001100 )
#570000000
0!
0%
#575000000
1!
1%
b111111001011 )
#580000000
0!
0%
#585000000
1!
1%
b111111001010 )
#590000000
0!
0%
#595000000
1!
1%
b111111001001 )
#600000000
0!
0%
#605000000
1!
1%
b111111001000 )
#610000000
0!
0%
#615000000
1!
1%
b111111000111 )
#620000000
0!
0%
#625000000
1!
1%
b111111000110 )
#630000000
0!
0%
#635000000
1!
1%
b111111000101 )
#640000000
0!
0%
#645000000
1!
1%
b111111000100 )
#650000000
0!
0%
#655000000
1!
1%
b111111000011 )
#660000000
0!
0%
#665000000
1!
1%
b111111000010 )
#670000000
0!
0%
#675000000
1!
1%
b111111000001 )
#680000000
0!
0%
#685000000
1!
1%
b111111000000 )
#690000000
0!
0%
#695000000
1!
1%
b111110111111 )
#700000000
0!
0%
#705000000
1!
1%
b111110111110 )
#710000000
0!
0%
#715000000
1!
1%
b111110111101 )
#720000000
0!
0%
#725000000
1!
1%
b111110111100 )
#730000000
0!
0%
#735000000
1!
1%
b111110111011 )
#740000000
0!
0%
#745000000
1!
1%
b111110111010 )
#750000000
0!
0%
#755000000
1!
1%
b111110111001 )
#760000000
0!
0%
#765000000
1!
1%
b111110111000 )
#770000000
0!
0%
#775000000
1!
1%
b111110110111 )
#780000000
0!
0%
#785000000
1!
1%
b111110110110 )
#790000000
0!
0%
#795000000
1!
1%
b111110110101 )
#800000000
0!
0%
#805000000
1!
1%
b111110110100 )
#810000000
0!
0%
#815000000
1!
1%
b111110110011 )
#820000000
0!
0%
#825000000
1!
1%
b111110110010 )
#830000000
0!
0%
#835000000
1!
1%
b111110110001 )
#840000000
0!
0%
#845000000
1!
1%
b111110110000 )
#850000000
0!
0%
#855000000
1!
1%
b111110101111 )
#860000000
0!
0%
#865000000
1!
1%
b111110101110 )
#870000000
0!
0%
#875000000
1!
1%
b111110101101 )
#880000000
0!
0%
#885000000
1!
1%
b111110101100 )
#890000000
0!
0%
#895000000
1!
1%
b111110101011 )
#900000000
0!
0%
#905000000
1!
1%
b111110101010 )
#910000000
0!
0%
#915000000
1!
1%
b111110101001 )
#920000000
0!
0%
#925000000
1!
1%
b111110101000 )
#930000000
0!
0%
#935000000
1!
1%
b111110100111 )
#940000000
0!
0%
#945000000
1!
1%
b111110100110 )
#950000000
0!
0%
#955000000
1!
1%
b111110100101 )
#960000000
0!
0%
#965000000
1!
1%
b111110100100 )
#970000000
0!
0%
#975000000
1!
1%
b111110100011 )
#980000000
0!
0%
#985000000
1!
1%
b111110100010 )
#990000000
0!
0%
#995000000
1!
1%
b111110100001 )
#1000000000
0!
0%
#1005000000
1!
1%
b111110100000 )
#1010000000
0!
0%
#1015000000
1!
1%
b111110011111 )
#1020000000
0!
0%
#1025000000
1!
1%
b111110011110 )
#1030000000
0!
0%
#1035000000
1!
1%
b111110011101 )
#1040000000
0!
0%
#1045000000
1!
1%
b111110011100 )
#1050000000
0!
0%
#1055000000
1!
1%
b111110011011 )
#1060000000
0!
0%
#1065000000
1!
1%
b111110011010 )
#1070000000
0!
0%
#1075000000
1!
1%
b111110011001 )
#1080000000
0!
0%
#1085000000
1!
1%
b111110011000 )
#1090000000
0!
0%
#1095000000
1!
1%
b111110010111 )
#1100000000
0!
0%
#1105000000
1!
1%
b111110010110 )
#1110000000
0!
0%
#1115000000
1!
1%
b111110010101 )
#1120000000
0!
0%
#1125000000
1!
1%
b111110010100 )
#1130000000
0!
0%
#1135000000
1!
1%
b111110010011 )
#1140000000
0!
0%
#1145000000
1!
1%
b111110010010 )
#1150000000
0!
0%
#1155000000
1!
1%
b111110010001 )
#1160000000
0!
0%
#1165000000
1!
1%
b111110010000 )
#1170000000
0!
0%
#1175000000
1!
1%
b111110001111 )
#1180000000
0!
0%
#1185000000
1!
1%
b111110001110 )
#1190000000
0!
0%
#1195000000
1!
1%
b111110001101 )
#1200000000
0!
0%
#1205000000
1!
1%
b111110001100 )
#1210000000
0!
0%
#1215000000
1!
1%
b111110001011 )
#1220000000
0!
0%
#1225000000
1!
1%
b111110001010 )
#1230000000
0!
0%
#1235000000
1!
1%
b111110001001 )
#1240000000
0!
0%
#1245000000
1!
1%
b111110001000 )
#1250000000
0!
0%
#1255000000
1!
1%
b111110000111 )
#1260000000
0!
0%
#1265000000
1!
1%
b111110000110 )
#1270000000
0!
0%
#1275000000
1!
1%
b111110000101 )
#1280000000
0!
0%
#1285000000
1!
1%
b111110000100 )
#1290000000
0!
0%
#1295000000
1!
1%
b111110000011 )
#1300000000
0!
0%
#1305000000
1!
1%
b111110000010 )
#1310000000
0!
0%
#1315000000
1!
1%
b111110000001 )
#1320000000
0!
0%
#1325000000
1!
1%
b111110000000 )
#1330000000
0!
0%
#1335000000
1!
1%
b111101111111 )
#1340000000
0!
0%
#1345000000
1!
1%
b111101111110 )
#1350000000
0!
0%
#1355000000
1!
1%
b111101111101 )
#1360000000
0!
0%
#1365000000
1!
1%
b111101111100 )
#1370000000
0!
0%
#1375000000
1!
1%
b111101111011 )
#1380000000
0!
0%
#1385000000
1!
1%
b111101111010 )
#1390000000
0!
0%
#1395000000
1!
1%
b111101111001 )
#1400000000
0!
0%
#1405000000
1!
1%
b111101111000 )
#1410000000
0!
0%
#1415000000
1!
1%
b111101110111 )
#1420000000
0!
0%
#1425000000
1!
1%
b111101110110 )
#1430000000
0!
0%
#1435000000
1!
1%
b111101110101 )
#1440000000
0!
0%
#1445000000
1!
1%
b111101110100 )
#1450000000
0!
0%
#1455000000
1!
1%
b111101110011 )
#1460000000
0!
0%
#1465000000
1!
1%
b111101110010 )
#1470000000
0!
0%
#1475000000
1!
1%
b111101110001 )
#1480000000
0!
0%
#1485000000
1!
1%
b111101110000 )
#1490000000
0!
0%
#1495000000
1!
1%
b111101101111 )
#1500000000
0!
0%
#1505000000
1!
1%
b111101101110 )
#1510000000
0!
0%
#1515000000
1!
1%
b111101101101 )
#1520000000
0!
0%
#1525000000
1!
1%
b111101101100 )
#1530000000
0!
0%
#1535000000
1!
1%
b111101101011 )
#1540000000
0!
0%
#1545000000
1!
1%
b111101101010 )
#1550000000
0!
0%
#1555000000
1!
1%
b111101101001 )
#1560000000
0!
0%
#1565000000
1!
1%
b111101101000 )
#1570000000
0!
0%
#1575000000
1!
1%
b111101100111 )
#1580000000
0!
0%
#1585000000
1!
1%
b111101100110 )
#1590000000
0!
0%
#1595000000
1!
1%
b111101100101 )
#1600000000
0!
0%
#1605000000
1!
1%
b111101100100 )
#1610000000
0!
0%
#1615000000
1!
1%
b111101100011 )
#1620000000
0!
0%
#1625000000
1!
1%
b111101100010 )
#1630000000
0!
0%
#1635000000
1!
1%
b111101100001 )
#1640000000
0!
0%
#1645000000
1!
1%
b111101100000 )
#1650000000
0!
0%
#1655000000
1!
1%
b111101011111 )
#1660000000
0!
0%
#1665000000
1!
1%
b111101011110 )
#1670000000
0!
0%
#1675000000
1!
1%
b111101011101 )
#1680000000
0!
0%
#1685000000
1!
1%
b111101011100 )
#1690000000
0!
0%
#1695000000
1!
1%
b111101011011 )
#1700000000
0!
0%
#1705000000
1!
1%
b111101011010 )
#1710000000
0!
0%
#1715000000
1!
1%
b111101011001 )
#1720000000
0!
0%
#1725000000
1!
1%
b111101011000 )
#1730000000
0!
0%
#1735000000
1!
1%
b111101010111 )
#1740000000
0!
0%
#1745000000
1!
1%
b111101010110 )
#1750000000
0!
0%
#1755000000
1!
1%
b111101010101 )
#1760000000
0!
0%
#1765000000
1!
1%
b111101010100 )
#1770000000
0!
0%
#1775000000
1!
1%
b111101010011 )
#1780000000
0!
0%
#1785000000
1!
1%
b111101010010 )
#1790000000
0!
0%
#1795000000
1!
1%
b111101010001 )
#1800000000
0!
0%
#1805000000
1!
1%
b111101010000 )
#1810000000
0!
0%
#1815000000
1!
1%
b111101001111 )
#1820000000
0!
0%
#1825000000
1!
1%
b111101001110 )
#1830000000
0!
0%
#1835000000
1!
1%
b111101001101 )
#1840000000
0!
0%
#1845000000
1!
1%
b111101001100 )
#1850000000
0!
0%
#1855000000
1!
1%
b111101001011 )
#1860000000
0!
0%
#1865000000
1!
1%
b111101001010 )
#1870000000
0!
0%
#1875000000
1!
1%
b111101001001 )
#1880000000
0!
0%
#1885000000
1!
1%
b111101001000 )
#1890000000
0!
0%
#1895000000
1!
1%
b111101000111 )
#1900000000
0!
0%
#1905000000
1!
1%
b111101000110 )
#1910000000
0!
0%
#1915000000
1!
1%
b111101000101 )
#1920000000
0!
0%
#1925000000
1!
1%
b111101000100 )
#1930000000
0!
0%
#1935000000
1!
1%
b111101000011 )
#1940000000
0!
0%
#1945000000
1!
1%
b111101000010 )
#1950000000
0!
0%
#1955000000
1!
1%
b111101000001 )
#1960000000
0!
0%
#1965000000
1!
1%
b111101000000 )
#1970000000
0!
0%
#1975000000
1!
1%
b111100111111 )
#1980000000
0!
0%
#1985000000
1!
1%
b111100111110 )
#1990000000
0!
0%
#1995000000
1!
1%
b111100111101 )
#2000000000
0!
0%
#2005000000
1!
1%
b111100111100 )
#2010000000
0!
0%
#2015000000
1!
1%
b111100111011 )
#2020000000
0!
0%
#2025000000
1!
1%
b111100111010 )
#2030000000
0!
0%
#2035000000
1!
1%
b111100111001 )
#2040000000
0!
0%
#2045000000
1!
1%
b111100111000 )
#2050000000
0!
0%
#2055000000
1!
1%
b111100110111 )
#2060000000
0!
0%
#2065000000
1!
1%
b111100110110 )
#2070000000
0!
0%
#2075000000
1!
1%
b111100110101 )
#2080000000
0!
0%
#2085000000
1!
1%
b111100110100 )
#2090000000
0!
0%
#2095000000
1!
1%
b111100110011 )
#2100000000
0!
0%
#2105000000
1!
1%
b111100110010 )
#2110000000
0!
0%
#2115000000
1!
1%
b111100110001 )
#2120000000
0!
0%
#2125000000
1!
1%
b111100110000 )
#2130000000
0!
0%
#2135000000
1!
1%
b111100101111 )
#2140000000
0!
0%
#2145000000
1!
1%
b111100101110 )
#2150000000
0!
0%
#2155000000
1!
1%
b111100101101 )
#2160000000
0!
0%
#2165000000
1!
1%
b111100101100 )
#2170000000
0!
0%
#2175000000
1!
1%
b111100101011 )
#2180000000
0!
0%
#2185000000
1!
1%
b111100101010 )
#2190000000
0!
0%
#2195000000
1!
1%
b111100101001 )
#2200000000
0!
0%
#2205000000
1!
1%
b111100101000 )
#2210000000
0!
0%
#2215000000
1!
1%
b111100100111 )
#2220000000
0!
0%
#2225000000
1!
1%
b111100100110 )
#2230000000
0!
0%
#2235000000
1!
1%
b111100100101 )
#2240000000
0!
0%
#2245000000
1!
1%
b111100100100 )
#2250000000
0!
0%
#2255000000
1!
1%
b111100100011 )
#2260000000
0!
0%
#2265000000
1!
1%
b111100100010 )
#2270000000
0!
0%
#2275000000
1!
1%
b111100100001 )
#2280000000
0!
0%
#2285000000
1!
1%
b111100100000 )
#2290000000
0!
0%
#2295000000
1!
1%
b111100011111 )
#2300000000
0!
0%
#2305000000
1!
1%
b111100011110 )
#2310000000
0!
0%
#2315000000
1!
1%
b111100011101 )
#2320000000
0!
0%
#2325000000
1!
1%
b111100011100 )
#2330000000
0!
0%
#2335000000
1!
1%
b111100011011 )
#2340000000
0!
0%
#2345000000
1!
1%
b111100011010 )
#2350000000
0!
0%
#2355000000
1!
1%
b111100011001 )
#2360000000
0!
0%
#2365000000
1!
1%
b111100011000 )
#2370000000
0!
0%
#2375000000
1!
1%
b111100010111 )
#2380000000
0!
0%
#2385000000
1!
1%
b111100010110 )
#2390000000
0!
0%
#2395000000
1!
1%
b111100010101 )
#2400000000
0!
0%
#2405000000
1!
1%
b111100010100 )
#2410000000
0!
0%
#2415000000
1!
1%
b111100010011 )
#2420000000
0!
0%
#2425000000
1!
1%
b111100010010 )
#2430000000
0!
0%
#2435000000
1!
1%
b111100010001 )
#2440000000
0!
0%
#2445000000
1!
1%
b111100010000 )
#2450000000
0!
0%
#2455000000
1!
1%
b111100001111 )
#2460000000
0!
0%
#2465000000
1!
1%
b111100001110 )
#2470000000
0!
0%
#2475000000
1!
1%
b111100001101 )
#2480000000
0!
0%
#2485000000
1!
1%
b111100001100 )
#2490000000
0!
0%
#2495000000
1!
1%
b111100001011 )
#2500000000
0!
0%
#2505000000
1!
1%
b111100001010 )
#2510000000
0!
0%
#2515000000
1!
1%
b111100001001 )
#2520000000
0!
0%
#2525000000
1!
1%
b111100001000 )
#2530000000
0!
0%
#2535000000
1!
1%
b111100000111 )
#2540000000
0!
0%
#2545000000
1!
1%
b111100000110 )
#2550000000
0!
0%
#2555000000
1!
1%
b111100000101 )
#2560000000
0!
0%
#2565000000
1!
1%
b111100000100 )
#2570000000
0!
0%
#2575000000
1!
1%
b111100000011 )
#2580000000
0!
0%
#2585000000
1!
1%
b111100000010 )
#2590000000
0!
0%
#2595000000
1!
1%
b111100000001 )
#2600000000
0!
0%
#2605000000
1!
1%
b111100000000 )
#2610000000
0!
0%
#2615000000
1!
1%
b111011111111 )
#2620000000
0!
0%
#2625000000
1!
1%
b111011111110 )
#2630000000
0!
0%
#2635000000
1!
1%
b111011111101 )
#2640000000
0!
0%
#2645000000
1!
1%
b111011111100 )
#2650000000
0!
0%
#2655000000
1!
1%
b111011111011 )
#2660000000
0!
0%
#2665000000
1!
1%
b111011111010 )
#2670000000
0!
0%
#2675000000
1!
1%
b111011111001 )
#2680000000
0!
0%
#2685000000
1!
1%
b111011111000 )
#2690000000
0!
0%
#2695000000
1!
1%
b111011110111 )
#2700000000
0!
0%
#2705000000
1!
1%
b111011110110 )
#2710000000
0!
0%
#2715000000
1!
1%
b111011110101 )
#2720000000
0!
0%
#2725000000
1!
1%
b111011110100 )
#2730000000
0!
0%
#2735000000
1!
1%
b111011110011 )
#2740000000
0!
0%
#2745000000
1!
1%
b111011110010 )
#2750000000
0!
0%
#2755000000
1!
1%
b111011110001 )
#2760000000
0!
0%
#2765000000
1!
1%
b111011110000 )
#2770000000
0!
0%
#2775000000
1!
1%
b111011101111 )
#2780000000
0!
0%
#2785000000
1!
1%
b111011101110 )
#2790000000
0!
0%
#2795000000
1!
1%
b111011101101 )
#2800000000
0!
0%
#2805000000
1!
1%
b111011101100 )
#2810000000
0!
0%
#2815000000
1!
1%
b111011101011 )
#2820000000
0!
0%
#2825000000
1!
1%
b111011101010 )
#2830000000
0!
0%
#2835000000
1!
1%
b111011101001 )
#2840000000
0!
0%
#2845000000
1!
1%
b111011101000 )
#2850000000
0!
0%
#2855000000
1!
1%
b111011100111 )
#2860000000
0!
0%
#2865000000
1!
1%
b111011100110 )
#2870000000
0!
0%
#2875000000
1!
1%
b111011100101 )
#2880000000
0!
0%
#2885000000
1!
1%
b111011100100 )
#2890000000
0!
0%
#2895000000
1!
1%
b111011100011 )
#2900000000
0!
0%
#2905000000
1!
1%
b111011100010 )
#2910000000
0!
0%
#2915000000
1!
1%
b111011100001 )
#2920000000
0!
0%
#2925000000
1!
1%
b111011100000 )
#2930000000
0!
0%
#2935000000
1!
1%
b111011011111 )
#2940000000
0!
0%
#2945000000
1!
1%
b111011011110 )
#2950000000
0!
0%
#2955000000
1!
1%
b111011011101 )
#2960000000
0!
0%
#2965000000
1!
1%
b111011011100 )
#2970000000
0!
0%
#2975000000
1!
1%
b111011011011 )
#2980000000
0!
0%
#2985000000
1!
1%
b111011011010 )
#2990000000
0!
0%
#2995000000
1!
1%
b111011011001 )
#3000000000
0!
0%
#3005000000
1!
1%
b111011011000 )
#3010000000
0!
0%
#3015000000
1!
1%
b111011010111 )
#3020000000
0!
0%
#3025000000
1!
1%
b111011010110 )
#3030000000
0!
0%
#3035000000
1!
1%
b111011010101 )
#3040000000
0!
0%
#3045000000
1!
1%
b111011010100 )
#3050000000
0!
0%
#3055000000
1!
1%
b111011010011 )
#3060000000
0!
0%
#3065000000
1!
1%
b111011010010 )
#3070000000
0!
0%
#3075000000
1!
1%
b111011010001 )
#3080000000
0!
0%
#3085000000
1!
1%
b111011010000 )
#3090000000
0!
0%
#3095000000
1!
1%
b111011001111 )
#3100000000
0!
0%
#3105000000
1!
1%
b111011001110 )
#3110000000
0!
0%
#3115000000
1!
1%
b111011001101 )
#3120000000
0!
0%
#3125000000
1!
1%
b111011001100 )
#3130000000
0!
0%
#3135000000
1!
1%
b111011001011 )
#3140000000
0!
0%
#3145000000
1!
1%
b111011001010 )
#3150000000
0!
0%
#3155000000
1!
1%
b111011001001 )
#3160000000
0!
0%
#3165000000
1!
1%
b111011001000 )
#3170000000
0!
0%
#3175000000
1!
1%
b111011000111 )
#3180000000
0!
0%
#3185000000
1!
1%
b111011000110 )
#3190000000
0!
0%
#3195000000
1!
1%
b111011000101 )
#3200000000
0!
0%
#3205000000
1!
1%
b111011000100 )
#3210000000
0!
0%
#3215000000
1!
1%
b111011000011 )
#3220000000
0!
0%
#3225000000
1!
1%
b111011000010 )
#3230000000
0!
0%
#3235000000
1!
1%
b111011000001 )
#3240000000
0!
0%
#3245000000
1!
1%
b111011000000 )
#3250000000
0!
0%
#3255000000
1!
1%
b111010111111 )
#3260000000
0!
0%
#3265000000
1!
1%
b111010111110 )
#3270000000
0!
0%
#3275000000
1!
1%
b111010111101 )
#3280000000
0!
0%
#3285000000
1!
1%
b111010111100 )
#3290000000
0!
0%
#3295000000
1!
1%
b111010111011 )
#3300000000
0!
0%
#3305000000
1!
1%
b111010111010 )
#3310000000
0!
0%
#3315000000
1!
1%
b111010111001 )
#3320000000
0!
0%
#3325000000
1!
1%
b111010111000 )
#3330000000
0!
0%
#3335000000
1!
1%
b111010110111 )
#3340000000
0!
0%
#3345000000
1!
1%
b111010110110 )
#3350000000
0!
0%
#3355000000
1!
1%
b111010110101 )
#3360000000
0!
0%
#3365000000
1!
1%
b111010110100 )
#3370000000
0!
0%
#3375000000
1!
1%
b111010110011 )
#3380000000
0!
0%
#3385000000
1!
1%
b111010110010 )
#3390000000
0!
0%
#3395000000
1!
1%
b111010110001 )
#3400000000
0!
0%
#3405000000
1!
1%
b111010110000 )
#3410000000
0!
0%
#3415000000
1!
1%
b111010101111 )
#3420000000
0!
0%
#3425000000
1!
1%
b111010101110 )
#3430000000
0!
0%
#3435000000
1!
1%
b111010101101 )
#3440000000
0!
0%
#3445000000
1!
1%
b111010101100 )
#3450000000
0!
0%
#3455000000
1!
1%
b111010101011 )
#3460000000
0!
0%
#3465000000
1!
1%
b111010101010 )
#3470000000
0!
0%
#3475000000
1!
1%
b111010101001 )
#3480000000
0!
0%
#3485000000
1!
1%
b111010101000 )
#3490000000
0!
0%
#3495000000
1!
1%
b111010100111 )
#3500000000
0!
0%
#3505000000
1!
1%
b111010100110 )
#3510000000
0!
0%
#3515000000
1!
1%
b111010100101 )
#3520000000
0!
0%
#3525000000
1!
1%
b111010100100 )
#3530000000
0!
0%
#3535000000
1!
1%
b111010100011 )
#3540000000
0!
0%
#3545000000
1!
1%
b111010100010 )
#3550000000
0!
0%
#3555000000
1!
1%
b111010100001 )
#3560000000
0!
0%
#3565000000
1!
1%
b111010100000 )
#3570000000
0!
0%
#3575000000
1!
1%
b111010011111 )
#3580000000
0!
0%
#3585000000
1!
1%
b111010011110 )
#3590000000
0!
0%
#3595000000
1!
1%
b111010011101 )
#3600000000
0!
0%
#3605000000
1!
1%
b111010011100 )
#3610000000
0!
0%
#3615000000
1!
1%
b111010011011 )
#3620000000
0!
0%
#3625000000
1!
1%
b111010011010 )
#3630000000
0!
0%
#3635000000
1!
1%
b111010011001 )
#3640000000
0!
0%
#3645000000
1!
1%
b111010011000 )
#3650000000
0!
0%
#3655000000
1!
1%
b111010010111 )
#3660000000
0!
0%
#3665000000
1!
1%
b111010010110 )
#3670000000
0!
0%
#3675000000
1!
1%
b111010010101 )
#3680000000
0!
0%
#3685000000
1!
1%
b111010010100 )
#3690000000
0!
0%
#3695000000
1!
1%
b111010010011 )
#3700000000
0!
0%
#3705000000
1!
1%
b111010010010 )
#3710000000
0!
0%
#3715000000
1!
1%
b111010010001 )
#3720000000
0!
0%
#3725000000
1!
1%
b111010010000 )
#3730000000
0!
0%
#3735000000
1!
1%
b111010001111 )
#3740000000
0!
0%
#3745000000
1!
1%
b111010001110 )
#3750000000
0!
0%
#3755000000
1!
1%
b111010001101 )
#3760000000
0!
0%
#3765000000
1!
1%
b111010001100 )
#3770000000
0!
0%
#3775000000
1!
1%
b111010001011 )
#3780000000
0!
0%
#3785000000
1!
1%
b111010001010 )
#3790000000
0!
0%
#3795000000
1!
1%
b111010001001 )
#3800000000
0!
0%
#3805000000
1!
1%
b111010001000 )
#3810000000
0!
0%
#3815000000
1!
1%
b111010000111 )
#3820000000
0!
0%
#3825000000
1!
1%
b111010000110 )
#3830000000
0!
0%
#3835000000
1!
1%
b111010000101 )
#3840000000
0!
0%
#3845000000
1!
1%
b111010000100 )
#3850000000
0!
0%
#3855000000
1!
1%
b111010000011 )
#3860000000
0!
0%
#3865000000
1!
1%
b111010000010 )
#3870000000
0!
0%
#3875000000
1!
1%
b111010000001 )
#3880000000
0!
0%
#3885000000
1!
1%
b111010000000 )
#3890000000
0!
0%
#3895000000
1!
1%
b111001111111 )
#3900000000
0!
0%
#3905000000
1!
1%
b111001111110 )
#3910000000
0!
0%
#3915000000
1!
1%
b111001111101 )
#3920000000
0!
0%
#3925000000
1!
1%
b111001111100 )
#3930000000
0!
0%
#3935000000
1!
1%
b111001111011 )
#3940000000
0!
0%
#3945000000
1!
1%
b111001111010 )
#3950000000
0!
0%
#3955000000
1!
1%
b111001111001 )
#3960000000
0!
0%
#3965000000
1!
1%
b111001111000 )
#3970000000
0!
0%
#3975000000
1!
1%
b111001110111 )
#3980000000
0!
0%
#3985000000
1!
1%
b111001110110 )
#3990000000
0!
0%
#3995000000
1!
1%
b111001110101 )
#4000000000
0!
0%
#4005000000
1!
1%
b111001110100 )
#4010000000
0!
0%
#4015000000
1!
1%
b111001110011 )
#4020000000
0!
0%
#4025000000
1!
1%
b111001110010 )
#4030000000
0!
0%
#4035000000
1!
1%
b111001110001 )
#4040000000
0!
0%
#4045000000
1!
1%
b111001110000 )
#4050000000
0!
0%
#4055000000
1!
1%
b111001101111 )
#4060000000
0!
0%
#4065000000
1!
1%
b111001101110 )
#4070000000
0!
0%
#4075000000
1!
1%
b111001101101 )
#4080000000
0!
0%
#4085000000
1!
1%
b111001101100 )
#4090000000
0!
0%
#4095000000
1!
1%
b111001101011 )
#4100000000
0!
0%
#4105000000
1!
1%
b111001101010 )
#4110000000
0!
0%
#4115000000
1!
1%
b111001101001 )
#4120000000
0!
0%
#4125000000
1!
1%
b111001101000 )
#4130000000
0!
0%
#4135000000
1!
1%
b111001100111 )
#4140000000
0!
0%
#4145000000
1!
1%
b111001100110 )
#4150000000
0!
0%
#4155000000
1!
1%
b111001100101 )
#4160000000
0!
0%
#4165000000
1!
1%
b111001100100 )
#4170000000
0!
0%
#4175000000
1!
1%
b111001100011 )
#4180000000
0!
0%
#4185000000
1!
1%
b111001100010 )
#4190000000
0!
0%
#4195000000
1!
1%
b111001100001 )
#4200000000
0!
0%
#4205000000
1!
1%
b111001100000 )
#4210000000
0!
0%
#4215000000
1!
1%
b111001011111 )
#4220000000
0!
0%
#4225000000
1!
1%
b111001011110 )
#4230000000
0!
0%
#4235000000
1!
1%
b111001011101 )
#4240000000
0!
0%
#4245000000
1!
1%
b111001011100 )
#4250000000
0!
0%
#4255000000
1!
1%
b111001011011 )
#4260000000
0!
0%
#4265000000
1!
1%
b111001011010 )
#4270000000
0!
0%
#4275000000
1!
1%
b111001011001 )
#4280000000
0!
0%
