Calculator/7_Seg_Driver.vhd
library IEEE;
use IEEE.STD_LOGIC_1164.ALL;

-- Uncomment the following library declaration if using
-- arithmetic functions with Signed or Unsigned values
use IEEE.NUMERIC_STD.ALL;

-- Uncomment the following library declaration if instantiating
-- any Xilinx leaf cells in this code.
--library UNISIM;
--use UNISIM.VComponents.all;

entity Seven_segment_driver is
  generic (
    size : integer := 20
  );
  Port (
    clk : in std_logic;
    rst : in std_logic;
    binary_input : in std_logic_vector( 15 downto 0 );
    CA, CB, CC, CD, CE, CF, CG, DP : out std_logic;
    AN : out std_logic_vector( 3 downto 0 )
  );

end Seven_segment_driver;

architecture Behavioral of Seven_segment_driver is

  -- We will use a counter to derive the frequency for the displays
  -- clk is 100 MHz, we use 3 bits to address the display, so we count every
  -- size - 3 bits. To get ~100 Hz per digit, we need 20 bits, so that we divide
  -- by 2^20.
  signal flick_counter : unsigned( size - 1 downto 0 );
  -- The digit is temporarily stored here
  signal digit : std_logic_vector( 3 downto 0 );
  -- Collect the values of the cathodes here
  signal cathodes : std_logic_vector( 7 downto 0 );

  -- Divide the input into different digits
  signal digit0 : std_logic_vector( 3 downto 0 );
  signal digit1 : std_logic_vector( 3 downto 0 );
  signal digit2 : std_logic_vector( 3 downto 0 );
  signal digit3 : std_logic_vector( 3 downto 0 );

  -- Select which digit to display
  signal selector : std_logic_vector( 1 downto 0 );

begin

  -- Update the digits
  digit0 <= binary_input( 3 downto 0 );
  digit1 <= binary_input( 7 downto 4 );
  digit2 <= binary_input( 11 downto 8 );
  digit3 <= binary_input( 15 downto 12 );

  -- Divide the clk
  process ( clk, rst ) begin
    if rst = '0' then
      flick_counter <= ( others => '0' );
    elsif rising_edge( clk ) then
      flick_counter <= flick_counter + 1;
    end if;
  end process;

  -- Update the selector
    selector <= std_logic_vector( flick_counter( size - 1 downto size - 2 ) );
  -- Select the anode
  with selector select
    AN <=
      "1110" when "00",
      "1101" when "01",
      "1011" when "10",
      "0111" when others;

  -- Select the digit
  with selector select
    digit <=
      digit0 when "00",
      digit1 when "01",
      digit2 when "10",
      digit3 when others;

  -- Decode the digit
  with digit select
    cathodes <=
      -- DP, CG, CF, CE, CD, CC, CB, CA
      "11000000" when "0000",
      "11111001" when "0001",
      "10100100" when "0010",
      "10110000" when "0011",
      "10011001" when "0100",
      "10010010" when "0101",
      "10000010" when "0110",
      "11111000" when "0111",
      "10000000" when "1000",
      "10010000" when "1001",
      "10001000" when "1010",
      "10000011" when "1011",
      "11000110" when "1100",
      "10100001" when "1101",
      "10000110" when "1110",
      "10001110" when others;

  DP <= cathodes( 7 );
  CG <= cathodes( 6 );
  CF <= cathodes( 5 );
  CE <= cathodes( 4 );
  CD <= cathodes( 3 );
  CC <= cathodes( 2 );
  CB <= cathodes( 1 );
  CA <= cathodes( 0 );

end Behavioral;

Calculator/seven_seg_testbench.vhd
library IEEE;
use IEEE.STD_LOGIC_1164.ALL;
use IEEE.NUMERIC_STD.ALL;

entity seven_seg_testbench is
end seven_seg_testbench;

architecture Behavioral of seven_seg_testbench is

    -- Component Declaration for the Unit Under Test (UUT)
    component Seven_segment_driver
    generic (
        size : integer := 20
    );
    Port (
        clk : in std_logic;
        rst : in std_logic;
        binary_input : in std_logic_vector( 15 downto 0 );
        CA, CB, CC, CD, CE, CF, CG, DP : out std_logic;
        AN : out std_logic_vector( 3 downto 0 )
    );
    end component;

    -- Signals to connect to UUT
    signal clk_tb : std_logic := '0';
    signal rst_tb : std_logic := '0';
    signal binary_input_tb : std_logic_vector( 15 downto 0 ) := (others => '0');
    signal CA_tb, CB_tb, CC_tb, CD_tb, CE_tb, CF_tb, CG_tb, DP_tb : std_logic;
    signal AN_tb : std_logic_vector( 3 downto 0 );

    constant clk_period : time := 10 ns;

begin
     -- Instantiate the Unit Under Test (UUT)
    uut: Seven_segment_driver
    generic map (
        size => 5
    ) port map (
        clk => clk_tb,
        rst => rst_tb,
        binary_input => binary_input_tb,
        CA => CA_tb,
        CB => CB_tb,
        CC => CC_tb,
        CD => CD_tb,
        CE => CE_tb,
        CF => CF_tb,
        CG => CG_tb,
        DP => DP_tb,
        AN => AN_tb
    );

    clock : process
    begin
        clk_tb <= '0';
        wait for clk_period / 2;
        clk_tb <= '1';
        wait for clk_period / 2;
    end process;

    main : process
    begin
        -- Reset the UUT
        rst_tb <= '0';
        wait for clk_period * 2;
        rst_tb <= '1';
        wait for clk_period * 2;

        -- Test different binary inputs
        binary_input_tb <= "0000000000000000"; -- 0
        wait for clk_period * 100;

        binary_input_tb <= "0000000000001001"; -- 9
        wait for clk_period * 100;

        binary_input_tb <= "0000000000010101"; -- 21
        wait for clk_period * 100;

        binary_input_tb <= "0000000011111111"; -- 255
        wait for clk_period * 100;

        binary_input_tb <= "0000111111111111"; -- 4095
        wait for clk_period * 100;

        binary_input_tb <= "1111111111111111"; -- -1 in signed
        wait for clk_period * 100;

        -- End simulation
        wait;
    end process;
end architecture Behavioral;

Calculator/Seven_Seg_Driver_waves.vcd
$date
  Sun Jan 11 12:23:29 2026
$end
$version
  GHDL v0
$end
$timescale
  1 fs
$end
$scope module standard $end
$upscope $end
$scope module std_logic_1164 $end
$upscope $end
$scope module numeric_std $end
$upscope $end
$scope module seven_seg_testbench $end
$var reg 1 ! clk_tb $end
$var reg 1 " rst_tb $end
$var reg 16 # binary_input_tb[15:0] $end
$var reg 1 $ ca_tb $end
$var reg 1 % cb_tb $end
$var reg 1 & cc_tb $end
$var reg 1 ' cd_tb $end
$var reg 1 ( ce_tb $end
$var reg 1 ) cf_tb $end
$var reg 1 * cg_tb $end
$var reg 1 + dp_tb $end
$var reg 4 , an_tb[3:0] $end
$scope module uut $end
$var reg 1 - clk $end
$var reg 1 . rst $end
$var reg 16 / binary_input[15:0] $end
$var reg 1 0 ca $end
$var reg 1 1 cb $end
$var reg 1 2 cc $end
$var reg 1 3 cd $end
$var reg 1 4 ce $end
$var reg 1 5 cf $end
$var reg 1 6 cg $end
$var reg 1 7 dp $end
$var reg 4 8 an[3:0] $end
$var reg 5 9 flick_counter[4:0] $end
$var reg 4 : digit[3:0] $end
$var reg 8 ; cathodes[7:0] $end
$var reg 4 < digit0[3:0] $end
$var reg 4 = digit1[3:0] $end
$var reg 4 > digit2[3:0] $end
$var reg 4 ? digit3[3:0] $end
$var reg 2 @ selector[1:0] $end
$upscope $end
$upscope $end
$enddefinitions $end
#0
0!
0"
b0000000000000000 #
0$
0%
0&
0'
0(
0)
1*
1+
b1110 ,
0-
0.
b0000000000000000 /
00
01
02
03
04
05
16
17
b1110 8
b00000 9
b0000 :
b11000000 ;
b0000 <
b0000 =
b0000 >
b0000 ?
b00 @
#5000000
1!
1-
#10000000
0!
0-
#15000000
1!
1-
#20000000
0!
1"
0-
1.
#25000000
1!
1-
b00001 9
#30000000
0!
0-
#35000000
1!
1-
b00010 9
#40000000
0!
0-
#45000000
1!
1-
b00011 9
#50000000
0!
0-
#55000000
1!
1-
b00100 9
#60000000
0!
0-
#65000000
1!
1-
b00101 9
#70000000
0!
0-
#75000000
1!
1-
b00110 9
#80000000
0!
0-
#85000000
1!
1-
b00111 9
#90000000
0!
0-
#95000000
1!
b1101 ,
1-
b1101 8
b01000 9
b01 @
#100000000
0!
0-
#105000000
1!
1-
b01001 9
#110000000
0!
0-
#115000000
1!
1-
b01010 9
#120000000
0!
0-
#125000000
1!
1-
b01011 9
#130000000
0!
0-
#135000000
1!
1-
b01100 9
#140000000
0!
0-
#145000000
1!
1-
b01101 9
#150000000
0!
0-
#155000000
1!
1-
b01110 9
#160000000
0!
0-
#165000000
1!
1-
b01111 9
#170000000
0!
0-
#175000000
1!
b1011 ,
1-
b1011 8
b10000 9
b10 @
#180000000
0!
0-
#185000000
1!
1-
b10001 9
#190000000
0!
0-
#195000000
1!
1-
b10010 9
#200000000
0!
0-
#205000000
1!
1-
b10011 9
#210000000
0!
0-
#215000000
1!
1-
b10100 9
#220000000
0!
0-
#225000000
1!
1-
b10101 9
#230000000
0!
0-
#235000000
1!
1-
b10110 9
#240000000
0!
0-
#245000000
1!
1-
b10111 9
#250000000
0!
0-
#255000000
1!
b0111 ,
1-
b0111 8
b11000 9
b11 @
#260000000
0!
0-
#265000000
1!
1-
b11001 9
#270000000
0!
0-
#275000000
1!
1-
b11010 9
#280000000
0!
0-
#285000000
1!
1-
b11011 9
#290000000
0!
0-
#295000000
1!
1-
b11100 9
#300000000
0!
0-
#305000000
1!
1-
b11101 9
#310000000
0!
0-
#315000000
1!
1-
b11110 9
#320000000
0!
0-
#325000000
1!
1-
b11111 9
#330000000
0!
0-
#335000000
1!
b1110 ,
1-
b1110 8
b00000 9
b00 @
#340000000
0!
0-
#345000000
1!
1-
b00001 9
#350000000
0!
0-
#355000000
1!
1-
b00010 9
#360000000
0!
0-
#365000000
1!
1-
b00011 9
#370000000
0!
0-
#375000000
1!
1-
b00100 9
#380000000
0!
0-
#385000000
1!
1-
b00101 9
#390000000
0!
0-
#395000000
1!
1-
b00110 9
#400000000
0!
0-
#405000000
1!
1-
b00111 9
#410000000
0!
0-
#415000000
1!
b1101 ,
1-
b1101 8
b01000 9
b01 @
#420000000
0!
0-
#425000000
1!
1-
b01001 9
#430000000
0!
0-
#435000000
1!
1-
b01010 9
#440000000
0!
0-
#445000000
1!
1-
b01011 9
#450000000
0!
0-
#455000000
1!
1-
b01100 9
#460000000
0!
0-
#465000000
1!
1-
b01101 9
#470000000
0!
0-
#475000000
1!
1-
b01110 9
#480000000
0!
0-
#485000000
1!
1-
b01111 9
#490000000
0!
0-
#495000000
1!
b1011 ,
1-
b1011 8
b10000 9
b10 @
#500000000
0!
0-
#505000000
1!
1-
b10001 9
#510000000
0!
0-
#515000000
1!
1-
b10010 9
#520000000
0!
0-
#525000000
1!
1-
b10011 9
#530000000
0!
0-
#535000000
1!
1-
b10100 9
#540000000
0!
0-
#545000000
1!
1-
b10101 9
#550000000
0!
0-
#555000000
1!
1-
b10110 9
#560000000
0!
0-
#565000000
1!
1-
b10111 9
#570000000
0!
0-
#575000000
1!
b0111 ,
1-
b0111 8
b11000 9
b11 @
#580000000
0!
0-
#585000000
1!
1-
b11001 9
#590000000
0!
0-
#595000000
1!
1-
b11010 9
#600000000
0!
0-
#605000000
1!
1-
b11011 9
#610000000
0!
0-
#615000000
1!
1-
b11100 9
#620000000
0!
0-
#625000000
1!
1-
b11101 9
#630000000
0!
0-
#635000000
1!
1-
b11110 9
#640000000
0!
0-
#645000000
1!
1-
b11111 9
#650000000
0!
0-
#655000000
1!
b1110 ,
1-
b1110 8
b00000 9
b00 @
#660000000
0!
0-
#665000000
1!
1-
b00001 9
#670000000
0!
0-
#675000000
1!
1-
b00010 9
#680000000
0!
0-
#685000000
1!
1-
b00011 9
#690000000
0!
0-
#695000000
1!
1-
b00100 9
#700000000
0!
0-
#705000000
1!
1-
b00101 9
#710000000
0!
0-
#715000000
1!
1-
b00110 9
#720000000
0!
0-
#725000000
1!
1-
b00111 9
#730000000
0!
0-
#735000000
1!
b1101 ,
1-
b1101 8
b01000 9
b01 @
#740000000
0!
0-
#745000000
1!
1-
b01001 9
#750000000
0!
0-
#755000000
1!
1-
b01010 9
#760000000
0!
0-
#765000000
1!
1-
b01011 9
#770000000
0!
0-
#775000000
1!
1-
b01100 9
#780000000
0!
0-
#785000000
1!
1-
b01101 9
#790000000
0!
0-
#795000000
1!
1-
b01110 9
#800000000
0!
0-
#805000000
1!
1-
b01111 9
#810000000
0!
0-
#815000000
1!
b1011 ,
1-
b1011 8
b10000 9
b10 @
#820000000
0!
0-
#825000000
1!
1-
b10001 9
#830000000
0!
0-
#835000000
1!
1-
b10010 9
#840000000
0!
0-
#845000000
1!
1-
b10011 9
#850000000
0!
0-
#855000000
1!
1-
b10100 9
#860000000
0!
0-
#865000000
1!
1-
b10101 9
#870000000
0!
0-
#875000000
1!
1-
b10110 9
#880000000
0!
0-
#885000000
1!
1-
b10111 9
#890000000
0!
0-
#895000000
1!
b0111 ,
1-
b0111 8
b11000 9
b11 @
#900000000
0!
0-
#905000000
1!
1-
b11001 9
#910000000
0!
0-
#915000000
1!
1-
b11010 9
#920000000
0!
0-
#925000000
1!
1-
b11011 9
#930000000
0!
0-
#935000000
1!
1-
b11100 9
#940000000
0!
0-
#945000000
1!
1-
b11101 9
#950000000
0!
0-
#955000000
1!
1-
b11110 9
#960000000
0!
0-
#965000000
1!
1-
b11111 9
#970000000
0!
0-
#975000000
1!
b1110 ,
1-
b1110 8
b00000 9
b00 @
#980000000
0!
0-
#985000000
1!
1-
b00001 9
#990000000
0!
0-
#995000000
1!
1-
b00010 9
#1000000000
0!
0-
#1005000000
1!
1-
b00011 9
#1010000000
0!
0-
#1015000000
1!
1-
b00100 9
#1020000000
0!
0-
#1025000000
1!
1-
b00101 9
#1030000000
0!
0-
#1035000000
1!
1-
b00110 9
#1040000000
0!
b0000000000001001 #
1(
0*
0-
b0000000000001001 /
14
06
b1001 :
b10010000 ;
b1001 <
#1045000000
1!
1-
b00111 9
#1050000000
0!
0-
#1055000000
1!
0(
1*
b1101 ,
1-
04
16
b1101 8
b01000 9
b0000 :
b11000000 ;
b01 @
#1060000000
0!
0-
#1065000000
1!
1-
b01001 9
#1070000000
0!
0-
#1075000000
1!
1-
b01010 9
#1080000000
0!
0-
#1085000000
1!
1-
b01011 9
#1090000000
0!
0-
#1095000000
1!
1-
b01100 9
#1100000000
0!
0-
#1105000000
1!
1-
b01101 9
#1110000000
0!
0-
#1115000000
1!
1-
b01110 9
#1120000000
0!
0-
#1125000000
1!
1-
b01111 9
#1130000000
0!
0-
#1135000000
1!
b1011 ,
1-
b1011 8
b10000 9
b10 @
#1140000000
0!
0-
#1145000000
1!
1-
b10001 9
#1150000000
0!
0-
#1155000000
1!
1-
b10010 9
#1160000000
0!
0-
#1165000000
1!
1-
b10011 9
#1170000000
0!
0-
#1175000000
1!
1-
b10100 9
#1180000000
0!
0-
#1185000000
1!
1-
b10101 9
#1190000000
0!
0-
#1195000000
1!
1-
b10110 9
#1200000000
0!
0-
#1205000000
1!
1-
b10111 9
#1210000000
0!
0-
#1215000000
1!
b0111 ,
1-
b0111 8
b11000 9
b11 @
#1220000000
0!
0-
#1225000000
1!
1-
b11001 9
#1230000000
0!
0-
#1235000000
1!
1-
b11010 9
#1240000000
0!
0-
#1245000000
1!
1-
b11011 9
#1250000000
0!
0-
#1255000000
1!
1-
b11100 9
#1260000000
0!
0-
#1265000000
1!
1-
b11101 9
#1270000000
0!
0-
#1275000000
1!
1-
b11110 9
#1280000000
0!
0-
#1285000000
1!
1-
b11111 9
#1290000000
0!
0-
#1295000000
1!
1(
0*
b1110 ,
1-
14
06
b1110 8
b00000 9
b1001 :
b10010000 ;
b00 @
#1300000000
0!
0-
#1305000000
1!
1-
b00001 9
#1310000000
0!
0-
#1315000000
1!
1-
b00010 9
#1320000000
0!
0-
#1325000000
1!
1-
b00011 9
#1330000000
0!
0-
#1335000000
1!
1-
b00100 9
#1340000000
0!
0-
#1345000000
1!
1-
b00101 9
#1350000000
0!
0-
#1355000000
1!
1-
b00110 9
#1360000000
0!
0-
#1365000000
1!
1-
b00111 9
#1370000000
0!
0-
#1375000000
1!
0(
1*
b1101 ,
1-
04
16
b1101 8
b01000 9
b0000 :
b11000000 ;
b01 @
#1380000000
0!
0-
#1385000000
1!
1-
b01001 9
#1390000000
0!
0-
#1395000000
1!
1-
b01010 9
#1400000000
0!
0-
#1405000000
1!
1-
b01011 9
#1410000000
0!
0-
#1415000000
1!
1-
b01100 9
#1420000000
0!
0-
#1425000000
1!
1-
b01101 9
#1430000000
0!
0-
#1435000000
1!
1-
b01110 9
#1440000000
0!
0-
#1445000000
1!
1-
b01111 9
#1450000000
0!
0-
#1455000000
1!
b1011 ,
1-
b1011 8
b10000 9
b10 @
#1460000000
0!
0-
#1465000000
1!
1-
b10001 9
#1470000000
0!
0-
#1475000000
1!
1-
b10010 9
#1480000000
0!
0-
#1485000000
1!
1-
b10011 9
#1490000000
0!
0-
#1495000000
1!
1-
b10100 9
#1500000000
0!
0-
#1505000000
1!
1-
b10101 9
#1510000000
0!
0-
#1515000000
1!
1-
b10110 9
#1520000000
0!
0-
#1525000000
1!
1-
b10111 9
#1530000000
0!
0-
#1535000000
1!
b0111 ,
1-
b0111 8
b11000 9
b11 @
#1540000000
0!
0-
#1545000000
1!
1-
b11001 9
#1550000000
0!
0-
#1555000000
1!
1-
b11010 9
#1560000000
0!
0-
#1565000000
1!
1-
b11011 9
#1570000000
0!
0-
#1575000000
1!
1-
b11100 9
#1580000000
0!
0-
#1585000000
1!
1-
b11101 9
#1590000000
0!
0-
#1595000000
1!
1-
b11110 9
#1600000000
0!
0-
#1605000000
1!
1-
b11111 9
#1610000000
0!
0-
#1615000000
1!
1(
0*
b1110 ,
1-
14
06
b1110 8
b00000 9
b1001 :
b10010000 ;
b00 @
#1620000000
0!
0-
#1625000000
1!
1-
b00001 9
#1630000000
0!
0-
#1635000000
1!
1-
b00010 9
#1640000000
0!
0-
#1645000000
1!
1-
b00011 9
#1650000000
0!
0-
#1655000000
1!
1-
b00100 9
#1660000000
0!
0-
#1665000000
1!
1-
b00101 9
#1670000000
0!
0-
#1675000000
1!
1-
b00110 9
#1680000000
0!
0-
#1685000000
1!
1-
b00111 9
#1690000000
0!
0-
#1695000000
1!
0(
1*
b1101 ,
1-
04
16
b1101 8
b01000 9
b0000 :
b11000000 ;
b01 @
#1700000000
0!
0-
#1705000000
1!
1-
b01001 9
#1710000000
0!
0-
#1715000000
1!
1-
b01010 9
#1720000000
0!
0-
#1725000000
1!
1-
b01011 9
#1730000000
0!
0-
#1735000000
1!
1-
b01100 9
#1740000000
0!
0-
#1745000000
1!
1-
b01101 9
#1750000000
0!
0-
#1755000000
1!
1-
b01110 9
#1760000000
0!
0-
#1765000000
1!
1-
b01111 9
#1770000000
0!
0-
#1775000000
1!
b1011 ,
1-
b1011 8
b10000 9
b10 @
#1780000000
0!
0-
#1785000000
1!
1-
b10001 9
#1790000000
0!
0-
#1795000000
1!
1-
b10010 9
#1800000000
0!
0-
#1805000000
1!
1-
b10011 9
#1810000000
0!
0-
#1815000000
1!
1-
b10100 9
#1820000000
0!
0-
#1825000000
1!
1-
b10101 9
#1830000000
0!
0-
#1835000000
1!
1-
b10110 9
#1840000000
0!
0-
#1845000000
1!
1-
b10111 9
#1850000000
0!
0-
#1855000000
1!
b0111 ,
1-
b0111 8
b11000 9
b11 @
#1860000000
0!
0-
#1865000000
1!
1-
b11001 9
#1870000000
0!
0-
#1875000000
1!
1-
b11010 9
#1880000000
0!
0-
#1885000000
1!
1-
b11011 9
#1890000000
0!
0-
#1895000000
1!
1-
b11100 9
#1900000000
0!
0-
#1905000000
1!
1-
b11101 9
#1910000000
0!
0-
#1915000000
1!
1-
b11110 9
#1920000000
0!
0-
#1925000000
1!
1-
b11111 9
#1930000000
0!
0-
#1935000000
1!
1(
0*
b1110 ,
1-
14
06
b1110 8
b00000 9
b1001 :
b10010000 ;
b00 @
#1940000000
0!
0-
#1945000000
1!
1-
b00001 9
#1950000000
0!
0-
#1955000000
1!
1-
b00010 9
#1960000000
0!
0-
#1965000000
1!
1-
b00011 9
#1970000000
0!
0-
#1975000000
1!
1-
b00100 9
#1980000000
0!
0-
#1985000000
1!
1-
b00101 9
#1990000000
0!
0-
#1995000000
1!
1-
b00110 9
#2000000000
0!
0-
#2005000000
1!
1-
b00111 9
#2010000000
0!
0-
#2015000000
1!
0(
1*
b1101 ,
1-
04
16
b1101 8
b01000 9
b0000 :
b11000000 ;
b01 @
#2020000000
0!
0-
#2025000000
1!
1-
b01001 9
#2030000000
0!
0-
#2035000000
1!
1-
b01010 9
#2040000000
0!
b0000000000010101 #
1$
1'
1(
1)
0-
b0000000000010101 /
10
13
14
15
b0001 :
b11111001 ;
b0101 <
b0001 =
#2045000000
1!
1-
b01011 9
#2050000000
0!
0-
#2055000000
1!
1-
b01100 9
#2060000000
0!
0-
#2065000000
1!
1-
b01101 9
#2070000000
0!
0-
#2075000000
1!
1-
b01110 9
#2080000000
0!
0-
#2085000000
1!
1-
b01111 9
#2090000000
0!
0-
#2095000000
1!
0$
0'
0(
0)
b1011 ,
1-
00
03
04
05
b1011 8
b10000 9
b0000 :
b11000000 ;
b10 @
#2100000000
0!
0-
#2105000000
1!
1-
b10001 9
#2110000000
0!
0-
#2115000000
1!
1-
b10010 9
#2120000000
0!
0-
#2125000000
1!
1-
b10011 9
#2130000000
0!
0-
#2135000000
1!
1-
b10100 9
#2140000000
0!
0-
#2145000000
1!
1-
b10101 9
#2150000000
0!
0-
#2155000000
1!
1-
b10110 9
#2160000000
0!
0-
#2165000000
1!
1-
b10111 9
#2170000000
0!
0-
#2175000000
1!
b0111 ,
1-
b0111 8
b11000 9
b11 @
#2180000000
0!
0-
#2185000000
1!
1-
b11001 9
#2190000000
0!
0-
#2195000000
1!
1-
b11010 9
#2200000000
0!
0-
#2205000000
1!
1-
b11011 9
#2210000000
0!
0-
#2215000000
1!
1-
b11100 9
#2220000000
0!
0-
#2225000000
1!
1-
b11101 9
#2230000000
0!
0-
#2235000000
1!
1-
b11110 9
#2240000000
0!
0-
#2245000000
1!
1-
b11111 9
#2250000000
0!
0-
#2255000000
1!
1%
1(
0*
b1110 ,
1-
11
14
06
b1110 8
b00000 9
b0101 :
b10010010 ;
b00 @
#2260000000
0!
0-
#2265000000
1!
1-
b00001 9
#2270000000
0!
0-
#2275000000
1!
1-
b00010 9
#2280000000
0!
0-
#2285000000
1!
1-
b00011 9
#2290000000
0!
0-
#2295000000
1!
1-
b00100 9
#2300000000
0!
0-
#2305000000
1!
1-
b00101 9
#2310000000
0!
0-
#2315000000
1!
1-
b00110 9
#2320000000
0!
0-
#2325000000
1!
1-
b00111 9
#2330000000
0!
0-
#2335000000
1!
1$
0%
1'
1)
1*
b1101 ,
1-
10
01
13
15
16
b1101 8
b01000 9
b0001 :
b11111001 ;
b01 @
#2340000000
0!
0-
#2345000000
1!
1-
b01001 9
#2350000000
0!
0-
#2355000000
1!
1-
b01010 9
#2360000000
0!
0-
#2365000000
1!
1-
b01011 9
#2370000000
0!
0-
#2375000000
1!
1-
b01100 9
#2380000000
0!
0-
#2385000000
1!
1-
b01101 9
#2390000000
0!
0-
#2395000000
1!
1-
b01110 9
#2400000000
0!
0-
#2405000000
1!
1-
b01111 9
#2410000000
0!
0-
#2415000000
1!
0$
0'
0(
0)
b1011 ,
1-
00
03
04
05
b1011 8
b10000 9
b0000 :
b11000000 ;
b10 @
#2420000000
0!
0-
#2425000000
1!
1-
b10001 9
#2430000000
0!
0-
#2435000000
1!
1-
b10010 9
#2440000000
0!
0-
#2445000000
1!
1-
b10011 9
#2450000000
0!
0-
#2455000000
1!
1-
b10100 9
#2460000000
0!
0-
#2465000000
1!
1-
b10101 9
#2470000000
0!
0-
#2475000000
1!
1-
b10110 9
#2480000000
0!
0-
#2485000000
1!
1-
b10111 9
#2490000000
0!
0-
#2495000000
1!
b0111 ,
1-
b0111 8
b11000 9
b11 @
#2500000000
0!
0-
#2505000000
1!
1-
b11001 9
#2510000000
0!
0-
#2515000000
1!
1-
b11010 9
#2520000000
0!
0-
#2525000000
1!
1-
b11011 9
#2530000000
0!
0-
#2535000000
1!
1-
b11100 9
#2540000000
0!
0-
#2545000000
1!
1-
b11101 9
#2550000000
0!
0-
#2555000000
1!
1-
b11110 9
#2560000000
0!
0-
#2565000000
1!
1-
b11111 9
#2570000000
0!
0-
#2575000000
1!
1%
1(
0*
b1110 ,
1-
11
14
06
b1110 8
b00000 9
b0101 :
b10010010 ;
b00 @
#2580000000
0!
0-
#2585000000
1!
1-
b00001 9
#2590000000
0!
0-
#2595000000
1!
1-
b00010 9
#2600000000
0!
0-
#2605000000
1!
1-
b00011 9
#2610000000
0!
0-
#2615000000
1!
1-
b00100 9
#2620000000
0!
0-
#2625000000
1!
1-
b00101 9
#2630000000
0!
0-
#2635000000
1!
1-
b00110 9
#2640000000
0!
0-
#2645000000
1!
1-
b00111 9
#2650000000
0!
0-
#2655000000
1!
1$
0%
1'
1)
1*
b1101 ,
1-
10
01
13
15
16
b1101 8
b01000 9
b0001 :
b11111001 ;
b01 @
#2660000000
0!
0-
#2665000000
1!
1-
b01001 9
#2670000000
0!
0-
#2675000000
1!
1-
b01010 9
#2680000000
0!
0-
#2685000000
1!
1-
b01011 9
#2690000000
0!
0-
#2695000000
1!
1-
b01100 9
#2700000000
0!
0-
#2705000000
1!
1-
b01101 9
#2710000000
0!
0-
#2715000000
1!
1-
b01110 9
#2720000000
0!
0-
#2725000000
1!
1-
b01111 9
#2730000000
0!
0-
#2735000000
1!
0$
0'
0(
0)
b1011 ,
1-
00
03
04
05
b1011 8
b10000 9
b0000 :
b11000000 ;
b10 @
#2740000000
0!
0-
#2745000000
1!
1-
b10001 9
#2750000000
0!
0-
#2755000000
1!
1-
b10010 9
#2760000000
0!
0-
#2765000000
1!
1-
b10011 9
#2770000000
0!
0-
#2775000000
1!
1-
b10100 9
#2780000000
0!
0-
#2785000000
1!
1-
b10101 9
#2790000000
0!
0-
#2795000000
1!
1-
b10110 9
#2800000000
0!
0-
#2805000000
1!
1-
b10111 9
#2810000000
0!
0-
#2815000000
1!
b0111 ,
1-
b0111 8
b11000 9
b11 @
#2820000000
0!
0-
#2825000000
1!
1-
b11001 9
#2830000000
0!
0-
#2835000000
1!
1-
b11010 9
#2840000000
0!
0-
#2845000000
1!
1-
b11011 9
#2850000000
0!
0-
#2855000000
1!
1-
b11100 9
#2860000000
0!
0-
#2865000000
1!
1-
b11101 9
#2870000000
0!
0-
#2875000000
1!
1-
b11110 9
#2880000000
0!
0-
#2885000000
1!
1-
b11111 9
#2890000000
0!
0-
#2895000000
1!
1%
1(
0*
b1110 ,
1-
11
14
06
b1110 8
b00000 9
b0101 :
b10010010 ;
b00 @
#2900000000
0!
0-
#2905000000
1!
1-
b00001 9
#2910000000
0!
0-
#2915000000
1!
1-
b00010 9
#2920000000
0!
0-
#2925000000
1!
1-
b00011 9
#2930000000
0!
0-
#2935000000
1!
1-
b00100 9
#2940000000
0!
0-
#2945000000
1!
1-
b00101 9
#2950000000
0!
0-
#2955000000
1!
1-
b00110 9
#2960000000
0!
0-
#2965000000
1!
1-
b00111 9
#2970000000
0!
0-
#2975000000
1!
1$
0%
1'
1)
1*
b1101 ,
1-
10
01
13
15
16
b1101 8
b01000 9
b0001 :
b11111001 ;
b01 @
#2980000000
0!
0-
#2985000000
1!
1-
b01001 9
#2990000000
0!
0-
#2995000000
1!
1-
b01010 9
#3000000000
0!
0-
#3005000000
1!
1-
b01011 9
#3010000000
0!
0-
#3015000000
1!
1-
b01100 9
#3020000000
0!
0-
#3025000000
1!
1-
b01101 9
#3030000000
0!
0-
#3035000000
1!
1-
b01110 9
#3040000000
0!
b0000000011111111 #
0$
1%
1&
0(
0)
0*
0-
b0000000011111111 /
00
11
12
04
05
06
b1111 :
b10001110 ;
b1111 <
b1111 =
#3045000000
1!
1-
b01111 9
#3050000000
0!
0-
#3055000000
1!
0%
0&
0'
1*
b1011 ,
1-
01
02
03
16
b1011 8
b10000 9
b0000 :
b11000000 ;
b10 @
#3060000000
0!
0-
#3065000000
1!
1-
b10001 9
#3070000000
0!
0-
#3075000000
1!
1-
b10010 9
#3080000000
0!
0-
#3085000000
1!
1-
b10011 9
#3090000000
0!
0-
#3095000000
1!
1-
b10100 9
#3100000000
0!
0-
#3105000000
1!
1-
b10101 9
#3110000000
0!
0-
#3115000000
1!
1-
b10110 9
#3120000000
0!
0-
#3125000000
1!
1-
b10111 9
#3130000000
0!
0-
#3135000000
1!
b0111 ,
1-
b0111 8
b11000 9
b11 @
#3140000000
0!
0-
#3145000000
1!
1-
b11001 9
#3150000000
0!
0-
#3155000000
1!
1-
b11010 9
#3160000000
0!
0-
#3165000000
1!
1-
b11011 9
#3170000000
0!
0-
#3175000000
1!
1-
b11100 9
#3180000000
0!
0-
#3185000000
1!
1-
b11101 9
#3190000000
0!
0-
#3195000000
1!
1-
b11110 9
#3200000000
0!
0-
#3205000000
1!
1-
b11111 9
#3210000000
0!
0-
#3215000000
1!
1%
1&
1'
0*
b1110 ,
1-
11
12
13
06
b1110 8
b00000 9
b1111 :
b10001110 ;
b00 @
#3220000000
0!
0-
#3225000000
1!
1-
b00001 9
#3230000000
0!
0-
#3235000000
1!
1-
b00010 9
#3240000000
0!
0-
#3245000000
1!
1-
b00011 9
#3250000000
0!
0-
#3255000000
1!
1-
b00100 9
#3260000000
0!
0-
#3265000000
1!
1-
b00101 9
#3270000000
0!
0-
#3275000000
1!
1-
b00110 9
#3280000000
0!
0-
#3285000000
1!
1-
b00111 9
#3290000000
0!
0-
#3295000000
1!
b1101 ,
1-
b1101 8
b01000 9
b01 @
#3300000000
0!
0-
#3305000000
1!
1-
b01001 9
#3310000000
0!
0-
#3315000000
1!
1-
b01010 9
#3320000000
0!
0-
#3325000000
1!
1-
b01011 9
#3330000000
0!
0-
#3335000000
1!
1-
b01100 9
#3340000000
0!
0-
#3345000000
1!
1-
b01101 9
#3350000000
0!
0-
#3355000000
1!
1-
b01110 9
#3360000000
0!
0-
#3365000000
1!
1-
b01111 9
#3370000000
0!
0-
#3375000000
1!
0%
0&
0'
1*
b1011 ,
1-
01
02
03
16
b1011 8
b10000 9
b0000 :
b11000000 ;
b10 @
#3380000000
0!
0-
#3385000000
1!
1-
b10001 9
#3390000000
0!
0-
#3395000000
1!
1-
b10010 9
#3400000000
0!
0-
#3405000000
1!
1-
b10011 9
#3410000000
0!
0-
#3415000000
1!
1-
b10100 9
#3420000000
0!
0-
#3425000000
1!
1-
b10101 9
#3430000000
0!
0-
#3435000000
1!
1-
b10110 9
#3440000000
0!
0-
